LICENSE
MANIFEST.in
README.md
requirements.txt
setup.py
pyauto/__init__.py
pyauto.digitalocean.egg-info/PKG-INFO
pyauto.digitalocean.egg-info/SOURCES.txt
pyauto.digitalocean.egg-info/dependency_links.txt
pyauto.digitalocean.egg-info/requires.txt
pyauto.digitalocean.egg-info/top_level.txt
pyauto/digitalocean/__init__.py
pyauto/digitalocean/commands.py
pyauto/digitalocean/config.py