Metadata-Version: 1.0
Name: pyauto.digitalocean
Version: 0.0.2a1
Summary: A module for programmatically managing Digitalocean droplets
Home-page: https://github.com/adamjaso/pyauto/tree/master/digitalocean
Author: Adam Jaso
Author-email: UNKNOWN
License: GNU General Public License V2
Platform: UNKNOWN
